mypptpkg/__init__.py
mypptpkg-0.0.1.dist-info/METADATA
mypptpkg-0.0.1.dist-info/WHEEL
mypptpkg-0.0.1.dist-info/top_level.txt
mypptpkg-0.0.1.dist-info/RECORD
