Metadata-Version: 2.4
Name: mypptpkg
Version: 0.0.1
Summary: A demo package that runs a function on import
Author-email: Your Name <you@example.com>
License: MIT
Requires-Python: >=3.7
